rosdock/__init__.py
rosdock/main.py
rosdock-0.0.1.dist-info/LICENSE
rosdock-0.0.1.dist-info/METADATA
rosdock-0.0.1.dist-info/WHEEL
rosdock-0.0.1.dist-info/top_level.txt
rosdock-0.0.1.dist-info/RECORD
