Metadata-Version: 2.1
Name: rosdock
Version: 0.0.1
Summary: An utility scripts for wrapping ros catkin project and use it with docker
Home-page: https://github.com/trinhtrannp/rosdock
Author: Trinh Tran
Author-email: trinhtran2151995@gmail.com
License: UNKNOWN
Platform: UNKNOWN
Classifier: Programming Language :: Python :: 3
Classifier: License :: OSI Approved :: MIT License
Classifier: Operating System :: OS Independent
Requires-Python: >=3.6
